whatsappez.py
whatsappez-0.0.1.dist-info/LICENSE
whatsappez-0.0.1.dist-info/METADATA
whatsappez-0.0.1.dist-info/WHEEL
whatsappez-0.0.1.dist-info/top_level.txt
whatsappez-0.0.1.dist-info/RECORD
