Metadata-Version: 2.1
Name: whatsappez
Version: 0.0.1
Summary: Whatsappez is a powerful Python module that empowers you to seamlessly integrate WhatsApp messaging within your on-premises environment
Home-page: https://github.com/Shlok221B/whatsapp-onprem
Author: Shlok Sawant
License: UNKNOWN
Keywords: Whatsapp Business API,Whatsapp,Whatsapp on premises
Platform: UNKNOWN
Classifier: Programming Language :: Python :: 3
Classifier: License :: OSI Approved :: MIT License
Classifier: Operating System :: OS Independent
Requires-Python: >=3.10
License-File: LICENSE
Requires-Dist: pybase64
Requires-Dist: requests
